[
    null,
    {
        "id": 1,
        "autoRemovalTiming": 0,
        "chanceByDamage": 100,
        "iconIndex": 1,
        "maxTurns": 1,
        "message1": " collapsed!",
        "message2": " defeated!",
        "message3": "",
        "message4": " stood up!",
        "minTurns": 1,
        "motion": 3,
        "name": "Defeated",
        "note": "ステート１番はＨＰが０になったときに\n自動的に付加されます。",
        "overlay": 0,
        "priority": 100,
        "releaseByDamage": false,
        "removeAtBattleEnd": false,
        "removeByDamage": false,
        "removeByRestriction": false,
        "removeByWalking": false,
        "restriction": 4,
        "stepsToRemove": 100,
        "traits": [
            {
                "code": 23,
                "dataId": 9,
                "value": 0
            }
        ]
    },
    {
        "id": 2,
        "autoRemovalTiming": 2,
        "chanceByDamage": 100,
        "description": "",
        "iconIndex": 0,
        "maxTurns": 1,
        "message1": "",
        "message2": "",
        "message3": "",
        "message4": "",
        "minTurns": 1,
        "motion": 0,
        "name": "Defense",
        "note": "",
        "overlay": 0,
        "priority": 0,
        "removeAtBattleEnd": true,
        "removeByDamage": false,
        "removeByRestriction": true,
        "removeByWalking": false,
        "restriction": 0,
        "stepsToRemove": 100,
        "traits": [
            {
                "code": 62,
                "dataId": 1,
                "value": 0
            }
        ]
    },
    {
        "id": 3,
        "autoRemovalTiming": 0,
        "chanceByDamage": 100,
        "description": "",
        "iconIndex": 0,
        "maxTurns": 1,
        "message1": "",
        "message2": "",
        "message3": "",
        "message4": "",
        "minTurns": 1,
        "motion": 0,
        "name": "Immortality",
        "note": "",
        "overlay": 0,
        "priority": 0,
        "removeAtBattleEnd": true,
        "removeByDamage": false,
        "removeByRestriction": false,
        "removeByWalking": false,
        "restriction": 0,
        "stepsToRemove": 100,
        "traits": [
            {
                "code": 14,
                "dataId": 1,
                "value": 0
            }
        ]
    },
    {
        "id": 4,
        "autoRemovalTiming": 0,
        "chanceByDamage": 100,
        "iconIndex": 2,
        "maxTurns": 1,
        "message1": " has been poisoned!",
        "message2": "Poisoned!",
        "message3": "",
        "message4": "'s poison has disappeared!",
        "minTurns": 1,
        "motion": 1,
        "overlay": 1,
        "name": "Poison",
        "note": "",
        "priority": 50,
        "releaseByDamage": false,
        "removeAtBattleEnd": false,
        "removeByDamage": false,
        "removeByRestriction": false,
        "removeByWalking": false,
        "restriction": 0,
        "stepsToRemove": 100,
        "traits": [
            {
                "code": 22,
                "dataId": 7,
                "value": -0.1
            }
        ]
    },
    {
        "id": 5,
        "autoRemovalTiming": 1,
        "chanceByDamage": 100,
        "iconIndex": 3,
        "maxTurns": 5,
        "message1": " is trapped in darkness!",
        "message2": " closed in the darkness!",
        "message3": "",
        "message4": "'s darkness disappeared!",
        "minTurns": 3,
        "motion": 1,
        "name": "Darkness",
        "note": "",
        "overlay": 2,
        "priority": 60,
        "releaseByDamage": false,
        "removeAtBattleEnd": true,
        "removeByDamage": false,
        "removeByRestriction": false,
        "removeByWalking": false,
        "restriction": 0,
        "stepsToRemove": 100,
        "traits": [
            {
                "code": 22,
                "dataId": 0,
                "value": -0.5
            }
        ]
    },
    {
        "id": 6,
        "autoRemovalTiming": 1,
        "chanceByDamage": 100,
        "iconIndex": 4,
        "maxTurns": 5,
        "message1": " fell silent!",
        "message2": " was silenced!",
        "message3": "",
        "message4": "'s silence was broken!",
        "minTurns": 3,
        "motion": 1,
        "name": "Silence",
        "note": "",
        "overlay": 3,
        "priority": 65,
        "releaseByDamage": false,
        "removeAtBattleEnd": true,
        "removeByDamage": false,
        "removeByRestriction": false,
        "removeByWalking": false,
        "restriction": 0,
        "stepsToRemove": 100,
        "traits": [
            {
                "code": 42,
                "dataId": 1,
                "value": 0
            }
        ]
    },
    {
        "id": 7,
        "autoRemovalTiming": 1,
        "chanceByDamage": 50,
        "iconIndex": 5,
        "maxTurns": 4,
        "message1": " became furious!",
        "message2": " was enraged!",
        "message3": "",
        "message4": " regained consciousness!",
        "minTurns": 2,
        "motion": 1,
        "name": "Fierce Anger",
        "note": "",
        "overlay": 4,
        "priority": 70,
        "releaseByDamage": false,
        "removeAtBattleEnd": true,
        "removeByDamage": true,
        "removeByRestriction": false,
        "removeByWalking": false,
        "restriction": 2,
        "stepsToRemove": 100,
        "traits": []
    },
    {
        "id": 8,
        "autoRemovalTiming": 1,
        "chanceByDamage": 50,
        "iconIndex": 6,
        "maxTurns": 4,
        "message1": " was confused!",
        "message2": " was confused!",
        "message3": "",
        "message4": " regained consciousness!",
        "minTurns": 2,
        "motion": 1,
        "name": "Confusion",
        "note": "",
        "overlay": 5,
        "priority": 75,
        "releaseByDamage": false,
        "removeAtBattleEnd": true,
        "removeByDamage": true,
        "removeByRestriction": false,
        "removeByWalking": false,
        "restriction": 2,
        "stepsToRemove": 100,
        "traits": []
    },
    {
        "id": 9,
        "autoRemovalTiming": 1,
        "chanceByDamage": 50,
        "iconIndex": 7,
        "maxTurns": 4,
        "message1": " was captivated!",
        "message2": " was captivated!",
        "message3": "",
        "message4": " regained consciousness!",
        "minTurns": 2,
        "motion": 1,
        "name": "Fascination",
        "note": "",
        "overlay": 6,
        "priority": 80,
        "releaseByDamage": false,
        "removeAtBattleEnd": true,
        "removeByDamage": true,
        "removeByRestriction": false,
        "removeByWalking": false,
        "restriction": 3,
        "stepsToRemove": 100,
        "traits": []
    },
    {
        "id": 10,
        "autoRemovalTiming": 1,
        "chanceByDamage": 100,
        "iconIndex": 8,
        "maxTurns": 5,
        "message1": " fell asleep!",
        "message2": " was put to sleep!",
        "message3": " is sleeping.",
        "message4": " woke up!",
        "minTurns": 3,
        "motion": 2,
        "name": "Sleep",
        "note": "",
        "overlay": 7,
        "priority": 90,
        "releaseByDamage": true,
        "removeAtBattleEnd": true,
        "removeByDamage": true,
        "removeByRestriction": false,
        "removeByWalking": false,
        "restriction": 4,
        "stepsToRemove": 100,
        "traits": [
            {
                "code": 22,
                "dataId": 1,
                "value": -1
            }
        ]
    },
    {
        "id": 11,
        "autoRemovalTiming": 0,
        "chanceByDamage": 100,
        "traits": [],
        "iconIndex": 0,
        "maxTurns": 1,
        "message1": "",
        "message2": "",
        "message3": "",
        "message4": "",
        "minTurns": 1,
        "motion": 0,
        "name": "",
        "note": "",
        "overlay": 0,
        "priority": 50,
        "removeAtBattleEnd": false,
        "removeByDamage": false,
        "removeByRestriction": false,
        "removeByWalking": false,
        "restriction": 0,
        "stepsToRemove": 100
    },
    {
        "id": 12,
        "autoRemovalTiming": 0,
        "chanceByDamage": 100,
        "iconIndex": 18,
        "maxTurns": 1,
        "message1": " has been poisoned!",
        "message2": "I applied a deadly poison!",
        "message3": "",
        "message4": "'s deadly poison has disappeared!",
        "minTurns": 1,
        "motion": 1,
        "overlay": 1,
        "name": "Venom",
        "note": "",
        "priority": 80,
        "releaseByDamage": false,
        "removeAtBattleEnd": false,
        "removeByDamage": false,
        "removeByRestriction": false,
        "removeByWalking": false,
        "restriction": 0,
        "stepsToRemove": 100,
        "traits": [
            {
                "code": 22,
                "dataId": 7,
                "value": -0.2
            }
        ]
    },
    {
        "id": 13,
        "autoRemovalTiming": 2,
        "chanceByDamage": 100,
        "traits": [],
        "iconIndex": 9,
        "maxTurns": 5,
        "message1": " is paralyzed!",
        "message2": " was paralyzed!",
        "message3": " is paralyzed.",
        "message4": "'s paralysis has been lifted!",
        "minTurns": 2,
        "motion": 1,
        "name": "Paralysis",
        "note": "",
        "overlay": 0,
        "priority": 90,
        "removeAtBattleEnd": true,
        "removeByDamage": false,
        "removeByRestriction": false,
        "removeByWalking": false,
        "restriction": 4,
        "stepsToRemove": 100
    },
    {
        "id": 14,
        "autoRemovalTiming": 2,
        "chanceByDamage": 100,
        "iconIndex": 78,
        "maxTurns": 1,
        "message1": " fell down!",
        "message2": " was knocked over!",
        "message3": " is falling down.",
        "message4": " stood up!",
        "minTurns": 1,
        "motion": 0,
        "name": "Topple",
        "note": "",
        "overlay": 0,
        "priority": 90,
        "releaseByDamage": true,
        "removeAtBattleEnd": true,
        "removeByDamage": false,
        "removeByRestriction": false,
        "removeByWalking": false,
        "restriction": 4,
        "stepsToRemove": 100,
        "traits": [
            {
                "code": 22,
                "dataId": 1,
                "value": -1
            }
        ]
    },
    {
        "id": 15,
        "autoRemovalTiming": 0,
        "chanceByDamage": 100,
        "traits": [],
        "iconIndex": 0,
        "maxTurns": 1,
        "message1": "",
        "message2": "",
        "message3": "",
        "message4": "",
        "minTurns": 1,
        "motion": 0,
        "name": "",
        "note": "",
        "overlay": 0,
        "priority": 50,
        "removeAtBattleEnd": false,
        "removeByDamage": false,
        "removeByRestriction": false,
        "removeByWalking": false,
        "restriction": 0,
        "stepsToRemove": 100
    },
    {
        "id": 16,
        "autoRemovalTiming": 2,
        "chanceByDamage": 100,
        "iconIndex": 5,
        "maxTurns": 6,
        "message1": " started bleeding!",
        "message2": " started bleeding!",
        "message3": "",
        "message4": "'s bleeding has stopped!",
        "minTurns": 3,
        "motion": 1,
        "overlay": 0,
        "name": "Bleeding",
        "note": "",
        "priority": 50,
        "releaseByDamage": false,
        "removeAtBattleEnd": true,
        "removeByDamage": false,
        "removeByRestriction": false,
        "removeByWalking": false,
        "restriction": 0,
        "stepsToRemove": 100,
        "traits": [
            {
                "code": 22,
                "dataId": 7,
                "value": -0.1
            },
            {
                "code": 21,
                "dataId": 2,
                "value": 0.9
            }
        ]
    },
    {
        "id": 17,
        "autoRemovalTiming": 0,
        "chanceByDamage": 100,
        "iconIndex": 10,
        "maxTurns": 6,
        "message1": " has been infected by a virus!",
        "message2": " has been infected by a virus!",
        "message3": "",
        "message4": "'s virus has been eradicated!",
        "minTurns": 3,
        "motion": 1,
        "overlay": 0,
        "name": "Virus",
        "note": "",
        "priority": 80,
        "releaseByDamage": false,
        "removeAtBattleEnd": false,
        "removeByDamage": false,
        "removeByRestriction": false,
        "removeByWalking": false,
        "restriction": 0,
        "stepsToRemove": 100,
        "traits": [
            {
                "code": 22,
                "dataId": 7,
                "value": -0.1
            },
            {
                "code": 22,
                "dataId": 8,
                "value": -0.2
            },
            {
                "code": 11,
                "dataId": 1,
                "value": 1.2
            },
            {
                "code": 11,
                "dataId": 2,
                "value": 1.2
            },
            {
                "code": 11,
                "dataId": 4,
                "value": 1.2
            }
        ]
    },
    {
        "id": 18,
        "autoRemovalTiming": 2,
        "chanceByDamage": 100,
        "iconIndex": 75,
        "maxTurns": 7,
        "message1": " is protected by a cyber defense wall!",
        "message2": " is protected by a cyber defense wall!",
        "message3": "",
        "message4": "'s cyber defense barrier has lost its effectiveness!",
        "minTurns": 7,
        "motion": 1,
        "overlay": 0,
        "name": "Cyber Defense Wall",
        "note": "",
        "priority": 90,
        "releaseByDamage": false,
        "removeAtBattleEnd": true,
        "removeByDamage": false,
        "removeByRestriction": false,
        "removeByWalking": false,
        "restriction": 0,
        "stepsToRemove": 100,
        "traits": [
            {
                "code": 13,
                "dataId": 17,
                "value": 0
            }
        ]
    },
    {
        "id": 19,
        "autoRemovalTiming": 0,
        "chanceByDamage": 100,
        "traits": [],
        "iconIndex": 0,
        "maxTurns": 1,
        "message1": "",
        "message2": "",
        "message3": "",
        "message4": "",
        "minTurns": 1,
        "motion": 0,
        "name": "",
        "note": "",
        "overlay": 0,
        "priority": 50,
        "removeAtBattleEnd": false,
        "removeByDamage": false,
        "removeByRestriction": false,
        "removeByWalking": false,
        "restriction": 0,
        "stepsToRemove": 100
    },
    {
        "id": 20,
        "autoRemovalTiming": 0,
        "chanceByDamage": 100,
        "traits": [],
        "iconIndex": 0,
        "maxTurns": 1,
        "message1": "",
        "message2": "",
        "message3": "",
        "message4": "",
        "minTurns": 1,
        "motion": 0,
        "name": "",
        "note": "",
        "overlay": 0,
        "priority": 50,
        "removeAtBattleEnd": false,
        "removeByDamage": false,
        "removeByRestriction": false,
        "removeByWalking": false,
        "restriction": 0,
        "stepsToRemove": 100
    },
    {
        "id": 21,
        "autoRemovalTiming": 0,
        "chanceByDamage": 100,
        "traits": [],
        "iconIndex": 0,
        "maxTurns": 1,
        "message1": "",
        "message2": "",
        "message3": "",
        "message4": "",
        "minTurns": 1,
        "motion": 0,
        "name": "",
        "note": "",
        "overlay": 0,
        "priority": 50,
        "removeAtBattleEnd": false,
        "removeByDamage": false,
        "removeByRestriction": false,
        "removeByWalking": false,
        "restriction": 0,
        "stepsToRemove": 100
    },
    {
        "id": 22,
        "autoRemovalTiming": 0,
        "chanceByDamage": 100,
        "traits": [],
        "iconIndex": 0,
        "maxTurns": 1,
        "message1": "",
        "message2": "",
        "message3": "",
        "message4": "",
        "minTurns": 1,
        "motion": 0,
        "name": "",
        "note": "",
        "overlay": 0,
        "priority": 50,
        "removeAtBattleEnd": false,
        "removeByDamage": false,
        "removeByRestriction": false,
        "removeByWalking": false,
        "restriction": 0,
        "stepsToRemove": 100
    },
    {
        "id": 23,
        "autoRemovalTiming": 0,
        "chanceByDamage": 100,
        "traits": [],
        "iconIndex": 0,
        "maxTurns": 1,
        "message1": "",
        "message2": "",
        "message3": "",
        "message4": "",
        "minTurns": 1,
        "motion": 0,
        "name": "",
        "note": "",
        "overlay": 0,
        "priority": 50,
        "removeAtBattleEnd": false,
        "removeByDamage": false,
        "removeByRestriction": false,
        "removeByWalking": false,
        "restriction": 0,
        "stepsToRemove": 100
    },
    {
        "id": 24,
        "autoRemovalTiming": 0,
        "chanceByDamage": 100,
        "traits": [],
        "iconIndex": 0,
        "maxTurns": 1,
        "message1": "",
        "message2": "",
        "message3": "",
        "message4": "",
        "minTurns": 1,
        "motion": 0,
        "name": "",
        "note": "",
        "overlay": 0,
        "priority": 50,
        "removeAtBattleEnd": false,
        "removeByDamage": false,
        "removeByRestriction": false,
        "removeByWalking": false,
        "restriction": 0,
        "stepsToRemove": 100
    },
    {
        "id": 25,
        "autoRemovalTiming": 0,
        "chanceByDamage": 100,
        "traits": [],
        "iconIndex": 0,
        "maxTurns": 1,
        "message1": "",
        "message2": "",
        "message3": "",
        "message4": "",
        "minTurns": 1,
        "motion": 0,
        "name": "",
        "note": "",
        "overlay": 0,
        "priority": 50,
        "removeAtBattleEnd": false,
        "removeByDamage": false,
        "removeByRestriction": false,
        "removeByWalking": false,
        "restriction": 0,
        "stepsToRemove": 100
    },
    {
        "id": 26,
        "autoRemovalTiming": 0,
        "chanceByDamage": 100,
        "traits": [],
        "iconIndex": 0,
        "maxTurns": 1,
        "message1": "",
        "message2": "",
        "message3": "",
        "message4": "",
        "minTurns": 1,
        "motion": 0,
        "name": "",
        "note": "",
        "overlay": 0,
        "priority": 50,
        "removeAtBattleEnd": false,
        "removeByDamage": false,
        "removeByRestriction": false,
        "removeByWalking": false,
        "restriction": 0,
        "stepsToRemove": 100
    },
    {
        "id": 27,
        "autoRemovalTiming": 0,
        "chanceByDamage": 100,
        "traits": [],
        "iconIndex": 0,
        "maxTurns": 1,
        "message1": "",
        "message2": "",
        "message3": "",
        "message4": "",
        "minTurns": 1,
        "motion": 0,
        "name": "",
        "note": "",
        "overlay": 0,
        "priority": 50,
        "removeAtBattleEnd": false,
        "removeByDamage": false,
        "removeByRestriction": false,
        "removeByWalking": false,
        "restriction": 0,
        "stepsToRemove": 100
    },
    {
        "id": 28,
        "autoRemovalTiming": 2,
        "chanceByDamage": 100,
        "traits": [
            {
                "code": 23,
                "dataId": 3,
                "value": 2
            }
        ],
        "iconIndex": 73,
        "maxTurns": 7,
        "message1": "",
        "message2": "",
        "message3": " is focusing on item support!",
        "message4": "'s item support state has ended.",
        "minTurns": 7,
        "motion": 0,
        "name": "Item Support",
        "note": "",
        "overlay": 0,
        "priority": 50,
        "removeAtBattleEnd": true,
        "removeByDamage": false,
        "removeByRestriction": false,
        "removeByWalking": false,
        "restriction": 0,
        "stepsToRemove": 100
    },
    {
        "id": 29,
        "autoRemovalTiming": 2,
        "chanceByDamage": 100,
        "traits": [
            {
                "code": 23,
                "dataId": 6,
                "value": 0.9
            },
            {
                "code": 23,
                "dataId": 7,
                "value": 0.9
            }
        ],
        "iconIndex": 66,
        "maxTurns": 5,
        "message1": "",
        "message2": "",
        "message3": "",
        "message4": "",
        "minTurns": 5,
        "motion": 0,
        "name": "Lightning Rod",
        "note": "",
        "overlay": 0,
        "priority": 50,
        "removeAtBattleEnd": true,
        "removeByDamage": false,
        "removeByRestriction": false,
        "removeByWalking": false,
        "restriction": 0,
        "stepsToRemove": 100
    },
    {
        "id": 30,
        "autoRemovalTiming": 2,
        "chanceByDamage": 100,
        "traits": [
            {
                "code": 22,
                "dataId": 7,
                "value": 0.1
            }
        ],
        "iconIndex": 84,
        "maxTurns": 5,
        "message1": " has entered a state of HP recovery!",
        "message2": " has entered a state of HP recovery!",
        "message3": "'s HP automatically recovers.",
        "message4": "'s HP recovery state has been lifted.",
        "minTurns": 5,
        "motion": 0,
        "name": "HP Regeneration",
        "note": "",
        "overlay": 0,
        "priority": 80,
        "removeAtBattleEnd": true,
        "removeByDamage": false,
        "removeByRestriction": false,
        "removeByWalking": false,
        "restriction": 0,
        "stepsToRemove": 100
    },
    {
        "id": 31,
        "autoRemovalTiming": 2,
        "chanceByDamage": 100,
        "traits": [
            {
                "code": 22,
                "dataId": 8,
                "value": 0.1
            }
        ],
        "iconIndex": 84,
        "maxTurns": 5,
        "message1": " has entered MP recovery state!",
        "message2": " has entered MP recovery state!",
        "message3": "'s MP automatically recovers.",
        "message4": "'s MP recovery state has been lifted.",
        "minTurns": 5,
        "motion": 0,
        "name": "MP Regeneration",
        "note": "",
        "overlay": 0,
        "priority": 80,
        "removeAtBattleEnd": true,
        "removeByDamage": false,
        "removeByRestriction": false,
        "removeByWalking": false,
        "restriction": 0,
        "stepsToRemove": 100
    },
    {
        "id": 32,
        "autoRemovalTiming": 2,
        "chanceByDamage": 100,
        "traits": [
            {
                "code": 22,
                "dataId": 1,
                "value": 1
            },
            {
                "code": 22,
                "dataId": 4,
                "value": 1
            }
        ],
        "iconIndex": 81,
        "maxTurns": 1,
        "message1": " entered an absolute evasion state!",
        "message2": " entered an absolute evasion state!",
        "message3": " is in an absolute evasion state.",
        "message4": "'s absolute evasion state has been lifted.",
        "minTurns": 1,
        "motion": 0,
        "name": "Absolute Evasion",
        "note": "",
        "overlay": 0,
        "priority": 50,
        "removeAtBattleEnd": true,
        "removeByDamage": false,
        "removeByRestriction": false,
        "removeByWalking": false,
        "restriction": 0,
        "stepsToRemove": 100
    },
    {
        "id": 33,
        "autoRemovalTiming": 1,
        "chanceByDamage": 100,
        "traits": [
            {
                "code": 61,
                "dataId": 0,
                "value": 1
            }
        ],
        "iconIndex": 82,
        "maxTurns": 5,
        "message1": "",
        "message2": "",
        "message3": " is in a state of action twice.",
        "message4": "",
        "minTurns": 5,
        "motion": 0,
        "name": "Double Action",
        "note": "",
        "overlay": 0,
        "priority": 100,
        "removeAtBattleEnd": true,
        "removeByDamage": false,
        "removeByRestriction": false,
        "removeByWalking": false,
        "restriction": 0,
        "stepsToRemove": 100
    },
    {
        "id": 34,
        "autoRemovalTiming": 2,
        "chanceByDamage": 100,
        "traits": [
            {
                "code": 22,
                "dataId": 1,
                "value": 0.5
            }
        ],
        "iconIndex": 69,
        "maxTurns": 5,
        "message1": "",
        "message2": "",
        "message3": "",
        "message4": "",
        "minTurns": 5,
        "motion": 0,
        "name": "Evasion",
        "note": "",
        "overlay": 0,
        "priority": 80,
        "removeAtBattleEnd": true,
        "removeByDamage": false,
        "removeByRestriction": false,
        "removeByWalking": false,
        "restriction": 0,
        "stepsToRemove": 100
    },
    {
        "id": 35,
        "autoRemovalTiming": 0,
        "chanceByDamage": 100,
        "iconIndex": 10,
        "maxTurns": 1,
        "message1": " has been affected by the miasma!",
        "message2": "I cast a miasma!",
        "message3": "",
        "message4": "The miasma of  has disappeared!",
        "minTurns": 1,
        "motion": 1,
        "overlay": 0,
        "name": "Miasma",
        "note": "",
        "priority": 90,
        "releaseByDamage": false,
        "removeAtBattleEnd": false,
        "removeByDamage": false,
        "removeByRestriction": false,
        "removeByWalking": false,
        "restriction": 0,
        "stepsToRemove": 100,
        "traits": [
            {
                "code": 22,
                "dataId": 7,
                "value": -0.1
            }
        ]
    },
    {
        "id": 36,
        "autoRemovalTiming": 0,
        "chanceByDamage": 100,
        "traits": [
            {
                "code": 61,
                "dataId": 0,
                "value": 1
            }
        ],
        "iconIndex": 82,
        "maxTurns": 3,
        "message1": "",
        "message2": "",
        "message3": "",
        "message4": "",
        "minTurns": 3,
        "motion": 0,
        "name": "Double Action (True)",
        "note": "",
        "overlay": 0,
        "priority": 100,
        "removeAtBattleEnd": false,
        "removeByDamage": false,
        "removeByRestriction": false,
        "removeByWalking": false,
        "restriction": 0,
        "stepsToRemove": 100
    },
    {
        "id": 37,
        "autoRemovalTiming": 1,
        "chanceByDamage": 100,
        "traits": [
            {
                "code": 22,
                "dataId": 2,
                "value": 1
            }
        ],
        "iconIndex": 87,
        "maxTurns": 1,
        "message1": "",
        "message2": "",
        "message3": "",
        "message4": "",
        "minTurns": 1,
        "motion": 0,
        "name": "Guaranteed Critical",
        "note": "",
        "overlay": 0,
        "priority": 100,
        "removeAtBattleEnd": true,
        "removeByDamage": false,
        "removeByRestriction": false,
        "removeByWalking": false,
        "restriction": 0,
        "stepsToRemove": 100
    },
    {
        "id": 38,
        "autoRemovalTiming": 0,
        "chanceByDamage": 100,
        "traits": [
            {
                "code": 21,
                "dataId": 0,
                "value": 2
            }
        ],
        "iconIndex": 82,
        "maxTurns": 4,
        "message1": "'s HP increased significantly!",
        "message2": "",
        "message3": "",
        "message4": "",
        "minTurns": 6,
        "motion": 0,
        "name": "HP Boost",
        "note": "",
        "overlay": 0,
        "priority": 100,
        "removeAtBattleEnd": true,
        "removeByDamage": false,
        "removeByRestriction": false,
        "removeByWalking": false,
        "restriction": 0,
        "stepsToRemove": 100
    },
    {
        "id": 39,
        "autoRemovalTiming": 0,
        "chanceByDamage": 100,
        "traits": [],
        "iconIndex": 0,
        "maxTurns": 1,
        "message1": "",
        "message2": "",
        "message3": "",
        "message4": "",
        "minTurns": 1,
        "motion": 0,
        "name": "",
        "note": "",
        "overlay": 0,
        "priority": 50,
        "removeAtBattleEnd": false,
        "removeByDamage": false,
        "removeByRestriction": false,
        "removeByWalking": false,
        "restriction": 0,
        "stepsToRemove": 100
    },
    {
        "id": 40,
        "autoRemovalTiming": 0,
        "chanceByDamage": 100,
        "traits": [],
        "iconIndex": 0,
        "maxTurns": 1,
        "message1": "",
        "message2": "",
        "message3": "",
        "message4": "",
        "minTurns": 1,
        "motion": 0,
        "name": "",
        "note": "",
        "overlay": 0,
        "priority": 50,
        "removeAtBattleEnd": false,
        "removeByDamage": false,
        "removeByRestriction": false,
        "removeByWalking": false,
        "restriction": 0,
        "stepsToRemove": 100
    }
]